threejs_viewer/__init__.py
threejs_viewer/__main__.py
threejs_viewer/animation.py
threejs_viewer/client.py
threejs_viewer/viewer.html
threejs_viewer-0.0.1.dist-info/METADATA
threejs_viewer-0.0.1.dist-info/WHEEL
threejs_viewer-0.0.1.dist-info/entry_points.txt
threejs_viewer-0.0.1.dist-info/RECORD
