Metadata-Version: 2.4
Name: threejs-viewer
Version: 0.0.1
Summary: Lightweight Three.js viewer controlled from Python via WebSocket
Project-URL: Homepage, https://github.com/thijsdamsma/threejs-viewer
Project-URL: Repository, https://github.com/thijsdamsma/threejs-viewer
Author: Thijs Damsma
License-Expression: MIT
Keywords: 3d,robotics,three.js,viewer,visualization,websocket
Classifier: Development Status :: 3 - Alpha
Classifier: Intended Audience :: Developers
Classifier: Intended Audience :: Science/Research
Classifier: License :: OSI Approved :: MIT License
Classifier: Programming Language :: Python :: 3
Classifier: Programming Language :: Python :: 3.11
Classifier: Programming Language :: Python :: 3.12
Classifier: Topic :: Multimedia :: Graphics :: 3D Rendering
Classifier: Topic :: Scientific/Engineering :: Visualization
Requires-Python: >=3.11
Requires-Dist: numpy>=1.24.0
Requires-Dist: websockets>=12.0
